MANIFEST.in
README
requirements.txt
setup.py
django_whippedcream.egg-info/PKG-INFO
django_whippedcream.egg-info/SOURCES.txt
django_whippedcream.egg-info/dependency_links.txt
django_whippedcream.egg-info/top_level.txt
whippedcream/__init__.py
whippedcream/api.py
whippedcream/fields.py
whippedcream/mixins.py
whippedcream/models.py
whippedcream/serializer.py
whippedcream/validation.py
whippedcream/views.py
whippedcream/runtests/__init__.py
whippedcream/runtests/settings.py
whippedcream/runtests/urls.py
whippedcream/tests/__init__.py
whippedcream/tests/resources.py
whippedcream/tests/test_basic.py
whippedcream/tests/urls.py