Metadata-Version: 1.1
Name: django-whippedcream
Version: 0.2.2
Summary: Utilities that make tastypie taste better.
Home-page: https://github.com/paulcwatts/django-whippedcream
Author: Paul Watts
Author-email: paulcwatts@gmail.com
License: BSD
Platform: UNKNOWN
Classifier: Environment :: Web Environment
Classifier: Framework :: Django
Classifier: Intended Audience :: Developers
Classifier: License :: OSI Approved :: BSD License
Classifier: Operating System :: OS Independent
Classifier: Programming Language :: Python :: 2.7
Classifier: Programming Language :: Python :: 3.4
Classifier: Programming Language :: Python :: 3.5
